wos/__init__.py
wos/client.py
wos/utils.py
wos/aaa/__init__.py
wos/aaa/hello.py
wos-0.2.7.data/scripts/wos
wos-0.2.7.dist-info/LICENSE
wos-0.2.7.dist-info/METADATA
wos-0.2.7.dist-info/WHEEL
wos-0.2.7.dist-info/top_level.txt
wos-0.2.7.dist-info/RECORD
