Metadata-Version: 2.1
Name: wos
Version: 0.2.7
Summary: Web of Science client using API v3.
Home-page: http://github.com/enricobacis/wos
Author: Enrico Bacis
Author-email: enrico.bacis@gmail.com
License: MIT
Keywords: wos isi web of science knowledge api client
Platform: UNKNOWN
Requires-Dist: limit
Requires-Dist: suds
